caqtus_devices/cameras/imaging_source_dmk33gr0134/__init__.py
caqtus_devices/cameras/imaging_source_dmk33gr0134/_compiler.py
caqtus_devices/cameras/imaging_source_dmk33gr0134/_extension.py
caqtus_devices/cameras/imaging_source_dmk33gr0134/py.typed
caqtus_devices/cameras/imaging_source_dmk33gr0134/configuration/__init__.py
caqtus_devices/cameras/imaging_source_dmk33gr0134/configuration/configuration.py
caqtus_devices/cameras/imaging_source_dmk33gr0134/configuration_editor/__init__.py
caqtus_devices/cameras/imaging_source_dmk33gr0134/configuration_editor/editor.py
caqtus_devices/cameras/imaging_source_dmk33gr0134/runtime/__init__.py
caqtus_devices/cameras/imaging_source_dmk33gr0134/runtime/imaging_source_camera.py
caqtus_devices/cameras/imaging_source_dmk33gr0134/runtime/tisgrabber/__init__.py
caqtus_devices/cameras/imaging_source_dmk33gr0134/runtime/tisgrabber/tisgrabber.py
caqtus_devices_imaging_source_dmk33gr0134-1.11.0.dist-info/METADATA
caqtus_devices_imaging_source_dmk33gr0134-1.11.0.dist-info/WHEEL
caqtus_devices_imaging_source_dmk33gr0134-1.11.0.dist-info/licenses/license.md
caqtus_devices_imaging_source_dmk33gr0134-1.11.0.dist-info/RECORD
