Metadata-Version: 2.4
Name: caqtus-devices-imaging-source-dmk33gr0134
Version: 1.11.0
Summary: Contains the caqtus device extension for the Imaging Source camera DMK 33GR0134.
Author-email: light-scattering-io <lecaqtus66@gmail.com>
License: Copyright 2024 Université Paris-Saclay
License-File: license.md
Requires-Python: >=3.12
Requires-Dist: caqtus-suite>=6.20
